src/wall_e.py
package_sieve-0.3.0.dist-info/LICENSE
package_sieve-0.3.0.dist-info/METADATA
package_sieve-0.3.0.dist-info/WHEEL
package_sieve-0.3.0.dist-info/entry_points.txt
package_sieve-0.3.0.dist-info/top_level.txt
package_sieve-0.3.0.dist-info/RECORD
