Metadata-Version: 2.1
Name: package-sieve
Version: 0.3.0
Summary: Collector of absolute 3rd party packages from existing projects
Home-page: https://github.com/FluffyDietEngine/wall-e
Author: Santhosh Solomon
Author-email: solomon.santhosh@gmail.com
License: Apache License 2.0
Keywords: package-sieve,wall-e,ci,automation,linter,stale-package-remover,developer-tools
Platform: any
Classifier: Operating System :: OS Independent
Classifier: Programming Language :: Python
Classifier: Programming Language :: Python :: 3
Classifier: License :: OSI Approved :: Apache Software License
Classifier: Intended Audience :: Developers
License-File: LICENSE
